OWNd/__init__.py
OWNd/__main__.py
OWNd/connection.py
OWNd/discovery.py
OWNd/message.py
OWNd2-0.7.51.dist-info/LICENSE
OWNd2-0.7.51.dist-info/METADATA
OWNd2-0.7.51.dist-info/WHEEL
OWNd2-0.7.51.dist-info/top_level.txt
OWNd2-0.7.51.dist-info/RECORD
