Metadata-Version: 2.1
Name: OWNd2
Version: 0.7.51
Summary: Python interface for the OpenWebNet protocol
Home-page: https://github.com/smf666/OWNd
Author: smf666
Author-email: yetanotherjulien@gmail.com
Classifier: Programming Language :: Python :: 3.8
Classifier: License :: OSI Approved :: GNU General Public License v3 (GPLv3)
Classifier: Operating System :: OS Independent
Requires-Python: >=3.8
License-File: LICENSE
Requires-Dist: aiohttp
Requires-Dist: pytz
Requires-Dist: python-dateutil
Requires-Dist: pyserial-asyncio
